req_iab/__init__.py
req_iab/request.py
req_iab-1.3.dist-info/LICENSE.txt
req_iab-1.3.dist-info/METADATA
req_iab-1.3.dist-info/WHEEL
req_iab-1.3.dist-info/top_level.txt
req_iab-1.3.dist-info/RECORD
