Metadata-Version: 2.1
Name: req-iab
Version: 1.3
Summary: I_am_back的requests项目
Home-page: UNKNOWN
Author: I_am_back
Author-email: 2682786816@qq.com
License: UNKNOWN
Platform: UNKNOWN
Classifier: Programming Language :: Python :: 3.8
Classifier: License :: OSI Approved :: MIT License
Classifier: Operating System :: OS Independent
Classifier: Natural Language :: Chinese (Simplified)
Classifier: Development Status :: 6 - Mature
